exportvisuals/__init__.py
exportvisuals-0.1.dist-info/LICENCE.txt
exportvisuals-0.1.dist-info/METADATA
exportvisuals-0.1.dist-info/WHEEL
exportvisuals-0.1.dist-info/top_level.txt
exportvisuals-0.1.dist-info/RECORD
