Metadata-Version: 2.1
Name: exportvisuals
Version: 0.1
Summary: Proteus exportvisuals File
Home-page: UNKNOWN
Author: Proteus Technology PVT. LTD.
Author-email: <apps@baseinformation.com>
License: UNKNOWN
Keywords: python,first package
Platform: UNKNOWN
Classifier: Development Status :: 3 - Alpha
Classifier: Intended Audience :: Education
Classifier: Programming Language :: Python :: 2
Classifier: Programming Language :: Python :: 3
Classifier: Operating System :: MacOS :: MacOS X
Classifier: Operating System :: Microsoft :: Windows
License-File: LICENCE.txt
Requires-Dist: pandas
Requires-Dist: openpyxl
Requires-Dist: pdfkit
Requires-Dist: imgkit
Requires-Dist: loggerutility
